.gitignore
HISTORY.rst
README.rst
setup.py
proxiedssl/__init__.py
proxiedssl/middleware.py
proxiedssl.egg-info/PKG-INFO
proxiedssl.egg-info/SOURCES.txt
proxiedssl.egg-info/dependency_links.txt
proxiedssl.egg-info/not-zip-safe
proxiedssl.egg-info/requires.txt
proxiedssl.egg-info/top_level.txt