Metadata-Version: 1.0
Name: proxiedssl
Version: 0.1.1
Summary: Django Middleware for handling proxied ssl
Home-page: https://github.com/benliles/django-proxiedssl-middleware
Author: Benjamin Liles
Author-email: benliles@gmail.com
License: UNKNOWN
Keywords: django middleware proxy fcgi wsgi ssl
Platform: UNKNOWN
Classifier: Framework :: Django
Classifier: Development Status :: 4 - Beta
Classifier: Programming Language :: Python
Classifier: Topic :: Software Development :: Libraries :: Python Modules
